{
    "nextPaletteID": 3,
    "palettes": {
        "custom1": {
            "id": "custom1",
            "name": "Palette name",
            "colors": [
                "#000000",
                "#FFFFFF",
                "#FF2121",
                "#C4A717",
                "#FF8135",
                "#FFF609",
                "#A0C2FD",
                "#5D8BDA",
                "#1E67E6",
                "#175187",
                "#787878",
                "#BEA989",
                "#FFE6C2",
                "#FFD599",
                "#0F0F0F",
                "#000000"
            ],
            "custom": true
        }
    }
}